{
  "reports": [
    {
      "missionName": "asdsda",
      "m": 5,
      "moneypenny": 4,
      "agentsSerialNumbers": [
        "007",
        "008"
      ],
      "agentsNames": [
        "name",
        "name2"
      ],
      "gadgetName": "wow",
      "timeCreated": 5464,
      "timeIssued": 3245,
      "qTime": 34534
    },
    {
      "missionName": "asdaaaaaaa",
      "m": 4,
      "moneypenny": 1,
      "agentsSerialNumbers": [
        "009",
        "006"
      ],
      "agentsNames": [
        "name3",
        "name4"
      ],
      "gadgetName": "11",
      "timeCreated": 12,
      "timeIssued": 4,
      "qTime": 55
    }
  ],
  "total": 5
}